kg2.py
kg2-1.1.0.dist-info/METADATA
kg2-1.1.0.dist-info/WHEEL
kg2-1.1.0.dist-info/licenses/LICENSE
kg2-1.1.0.dist-info/RECORD
