Metadata-Version: 2.3
Name: kg2
Version: 1.1.0
Summary: A tool for models and formulas in Paraconsistent Gödel Modal Logic.
Project-URL: Homepage, https://github.com/joseoliveirajr/kg2
Project-URL: Bug Tracker, https://github.com/joseoliveirajr/kg2/issues
Author-email: "José C. Oliveira" <josecarlosdeoliveirajr@gmail.com>, Sophia Knight <sophia.knight@gmail.com>
Maintainer-email: "José C. Oliveira" <josecarlosdeoliveirajr@gmail.com>
License: MIT License
License-File: LICENSE
Classifier: Development Status :: 5 - Production/Stable
Classifier: Intended Audience :: Science/Research
Classifier: License :: OSI Approved :: MIT License
Classifier: Operating System :: OS Independent
Classifier: Topic :: Scientific/Engineering
Requires-Python: >=3.10
